live_vlm_webui/__init__.py
live_vlm_webui/gpu_monitor.py
live_vlm_webui/rtsp_track.py
live_vlm_webui/server.py
live_vlm_webui/video_processor.py
live_vlm_webui/vlm_service.py
live_vlm_webui/static/index.html
live_vlm_webui/static/favicon/apple-touch-icon.png
live_vlm_webui/static/favicon/favicon-96x96.png
live_vlm_webui/static/favicon/favicon.ico
live_vlm_webui/static/favicon/favicon.svg
live_vlm_webui/static/favicon/site.webmanifest
live_vlm_webui/static/favicon/web-app-manifest-192x192.png
live_vlm_webui/static/favicon/web-app-manifest-512x512.png
live_vlm_webui/static/images/.gitkeep
live_vlm_webui/static/images/README.md
live_vlm_webui/static/images/dgx-spark_256px.png
live_vlm_webui/static/images/jetson-agx-orin-devkit_256px.png
live_vlm_webui/static/images/jetson-agx-thor-devkit_256px.png
live_vlm_webui/static/images/jetson-orin-nano-devkit_217px.png
live_vlm_webui/static/images/m48-gpu-ampere-256px-grn.png
live_vlm_webui/static/images/m48-gpu-chip-text-256px-grn.png
live_vlm_webui/static/images/m48-laptop-256px-blk.png
live_vlm_webui/static/images/m48-laptop-256px-wht.png
live_vlm_webui/static/images/m48-workstation-256px-blk.png
live_vlm_webui/static/images/m48-workstation-256px-wht.png
live_vlm_webui/static/images/simple-logo.svg
live_vlm_webui-0.2.1.dist-info/licenses/LICENSE
live_vlm_webui-0.2.1.dist-info/METADATA
live_vlm_webui-0.2.1.dist-info/WHEEL
live_vlm_webui-0.2.1.dist-info/entry_points.txt
live_vlm_webui-0.2.1.dist-info/top_level.txt
live_vlm_webui-0.2.1.dist-info/RECORD
