Metadata-Version: 2.4
Name: live-vlm-webui
Version: 0.2.1
Summary: Real-time Vision Language Model interaction web interface
Author: NVIDIA Corporation
License: Apache-2.0
Project-URL: Homepage, https://github.com/nvidia-ai-iot/live-vlm-webui
Project-URL: Documentation, https://github.com/nvidia-ai-iot/live-vlm-webui/tree/main/docs
Project-URL: Repository, https://github.com/nvidia-ai-iot/live-vlm-webui
Project-URL: Issues, https://github.com/nvidia-ai-iot/live-vlm-webui/issues
Project-URL: Changelog, https://github.com/nvidia-ai-iot/live-vlm-webui/releases
Keywords: vision,ai,vlm,vision-language-model,webui,nvidia,real-time,webrtc,webcam,ollama,vllm
Classifier: Development Status :: 4 - Beta
Classifier: Intended Audience :: Developers
Classifier: Intended Audience :: Science/Research
Classifier: Topic :: Scientific/Engineering :: Artificial Intelligence
Classifier: Topic :: Multimedia :: Video
Classifier: License :: OSI Approved :: Apache Software License
Classifier: Programming Language :: Python :: 3
Classifier: Programming Language :: Python :: 3.10
Classifier: Programming Language :: Python :: 3.11
Classifier: Programming Language :: Python :: 3.12
Classifier: Operating System :: POSIX :: Linux
Classifier: Operating System :: MacOS
Requires-Python: >=3.10
License-File: LICENSE
Requires-Dist: aiohttp>=3.9.5
Requires-Dist: aiohttp-cors>=0.7.0
Requires-Dist: aiortc>=1.9.0
Requires-Dist: opencv-python>=4.10.0
Requires-Dist: numpy>=1.26.4
Requires-Dist: Pillow>=10.4.0
Requires-Dist: openai>=1.54.3
Requires-Dist: httpx>=0.27.2
Requires-Dist: av>=12.3.0
Requires-Dist: nvidia-ml-py>=11.5.0
Requires-Dist: psutil>=5.9.8
Provides-Extra: dev
Requires-Dist: pytest>=7.0; extra == "dev"
Requires-Dist: pytest-asyncio>=0.21.0; extra == "dev"
Requires-Dist: black>=23.0; extra == "dev"
Requires-Dist: ruff>=0.1.0; extra == "dev"
Requires-Dist: mypy>=1.0; extra == "dev"
Dynamic: license-file
